thonnycontrib/codelive/CRDT.py
thonnycontrib/codelive/__init__.py
thonnycontrib/codelive/client.py
thonnycontrib/codelive/crypt.py
thonnycontrib/codelive/mqtt_connection.py
thonnycontrib/codelive/patched_callbacks.py
thonnycontrib/codelive/user.py
thonnycontrib/codelive/user_management.py
thonnycontrib/codelive/utils.py
thonnycontrib/codelive/res/bug-16.png
thonnycontrib/codelive/res/bug-24.png
thonnycontrib/codelive/res/cursor.png
thonnycontrib/codelive/res/default_values.py
thonnycontrib/codelive/res/green_people.png
thonnycontrib/codelive/res/people-yellow-small.png
thonnycontrib/codelive/res/red_people.png
thonnycontrib/codelive/res/red_people_transp.png
thonnycontrib/codelive/views/create_session.py
thonnycontrib/codelive/views/hinttext.py
thonnycontrib/codelive/views/join_session.py
thonnycontrib/codelive/views/textspin.py
thonnycontrib/codelive/views/toolbar_popup.py
thonnycontrib/codelive/views/session_status/dialog.py
thonnycontrib/codelive/views/session_status/scrollable_frame.py
thonnycontrib/codelive/views/session_status/user_list.py
thonnycontrib/codelive/views/session_status/res/bug-16.png
thonnycontrib/codelive/views/session_status/res/bug-24.png
thonny_codelive-0.0.4.dist-info/LICENSE
thonny_codelive-0.0.4.dist-info/METADATA
thonny_codelive-0.0.4.dist-info/WHEEL
thonny_codelive-0.0.4.dist-info/top_level.txt
thonny_codelive-0.0.4.dist-info/RECORD
